<?xml version="1.0" encoding="utf-16"?>
<ClassificationGroup xmlns:xsd="http://www.w3.org/2001/XMLSchema" xmlns:xsi="http://www.w3.org/2001/XMLSchema-instance">
  <Identity>
    <Id>FF5E510F58144852B1710175FC4654C5</Id>
    <AutomaticallyPopulate>true</AutomaticallyPopulate>
    <Version>7</Version>
    <Name>Leifbillionproject</Name>
  </Identity>
  <Name>Leifbillionproject</Name>
  <Description />
  <Status>Released</Status>
  <IsShared>true</IsShared>
  <Category>
    <Id>201F370CA5164F76ADDD8EEEFF666AF7</Id>
    <AutomaticallyPopulate>true</AutomaticallyPopulate>
    <Name>Default Category</Name>
  </Category>
  <DocumentGroups>
    <DocumentGroupIdentity>
      <Id>FF5E510F58144852B1710175FC4654C5</Id>
      <AutomaticallyPopulate>true</AutomaticallyPopulate>
      <Version>7</Version>
      <Name>Leifbillionproject</Name>
    </DocumentGroupIdentity>
  </DocumentGroups>
  <LastModifiedDate>2021-11-03T13:28:25.893</LastModifiedDate>
  <LastModifiedUser>
    <Id>ECC398BCAD4F4D9388E9B33B5A6C0EF7</Id>
    <AutomaticallyPopulate>true</AutomaticallyPopulate>
    <Name />
    <ResourceType>Worker</ResourceType>
    <EmailAddress />
    <UserId />
    <ManagerialLevel>0</ManagerialLevel>
  </LastModifiedUser>
  <LockedBy>
    <Id>37B30C5D37034F3C92842C76E7BC18D3</Id>
    <AutomaticallyPopulate>true</AutomaticallyPopulate>
    <Name>Sunanda.Varma</Name>
    <ResourceType>Worker</ResourceType>
    <EmailAddress />
    <UserId />
    <ManagerialLevel>0</ManagerialLevel>
  </LockedBy>
  <LockedByModule>TotalAgilityDesigner</LockedByModule>
  <ClassificationOnlineLearningEnabled>false</ClassificationOnlineLearningEnabled>
  <ClassificationMaxDocCount>2000</ClassificationMaxDocCount>
  <ResourceAccessTokens>
    <ResourceAccess>
      <ResourceIdentity>
        <Id>7DF43CCDF24611D2804B00104B71BD15</Id>
        <AutomaticallyPopulate>true</AutomaticallyPopulate>
        <Name>Everyone</Name>
        <ResourceType>GroupOfWorkers</ResourceType>
        <EmailAddress />
        <UserId />
        <ManagerialLevel>0</ManagerialLevel>
      </ResourceIdentity>
      <AccessType>MaintenanceAccess</AccessType>
      <PermissionType>FullControl</PermissionType>
    </ResourceAccess>
  </ResourceAccessTokens>
  <ResourcePermissionType>NoAccess</ResourcePermissionType>
</ClassificationGroup>