<?xml version="1.0" encoding="utf-16"?>
<SpaPackage xmlns:xsd="http://www.w3.org/2001/XMLSchema" xmlns:xsi="http://www.w3.org/2001/XMLSchema-instance">
  <SpaPackageIdentity>
    <Id>0425E95C34A84421AEF404728FAFB0E4</Id>
    <Name>qwerty</Name>
    <Version>5</Version>
  </SpaPackageIdentity>
  <Description>123</Description>
  <CategoryIdentity>
    <Id>62E18169A4724202B42EBF7C3FDAF9E9</Id>
    <AutomaticallyPopulate>true</AutomaticallyPopulate>
    <Name>GIT DATA</Name>
  </CategoryIdentity>
  <LastModifiedDateTime>2021-09-30T00:46:09.2</LastModifiedDateTime>
  <LastModifiedResource>
    <Id>37B30C5D37034F3C92842C76E7BC18D3</Id>
    <AutomaticallyPopulate>true</AutomaticallyPopulate>
    <Name>Sunanda.Varma</Name>
    <ResourceType>Worker</ResourceType>
    <EmailAddress />
    <UserId />
    <ManagerialLevel>0</ManagerialLevel>
  </LastModifiedResource>
  <Data>
    <Processes>
      <ProcessIdentity>
        <Id>2C3638ABABB1C0FA631FC560A1696BC0</Id>
        <AutomaticallyPopulate>true</AutomaticallyPopulate>
        <Version>3</Version>
        <Name>TestSavedCd</Name>
      </ProcessIdentity>
      <ProcessIdentity>
        <Id>3ED872430D2C1F299F96199716FE964E</Id>
        <AutomaticallyPopulate>true</AutomaticallyPopulate>
        <Version>3</Version>
        <Name>TestSavedFrag</Name>
      </ProcessIdentity>
    </Processes>
    <ProcessExportOption>
      <ExportResources>false</ExportResources>
      <ExportGroupResourceMembers>false</ExportGroupResourceMembers>
      <ExportResourcesExtensions>false</ExportResourcesExtensions>
      <ExportCategories>false</ExportCategories>
      <WithCategoryParentage>false</WithCategoryParentage>
      <GeneralizedExport>false</GeneralizedExport>
      <ExportDotNetReferencesWithPath>true</ExportDotNetReferencesWithPath>
      <ExportCaseFragments>false</ExportCaseFragments>
      <ExportTemplateSkins>false</ExportTemplateSkins>
      <ExportExtractionClassificationData>true</ExportExtractionClassificationData>
      <ExportGlobalDataModels>false</ExportGlobalDataModels>
      <ExportProcessDataModels>false</ExportProcessDataModels>
      <ExportType>None</ExportType>
      <Version>0</Version>
      <ExportServerVariables>true</ExportServerVariables>
      <XmlExpressionVariables />
      <PreloadScript>1</PreloadScript>
      <SleepDuration>0</SleepDuration>
      <CategoryIds />
      <ProcessDocument>false</ProcessDocument>
      <ProcessViewer>false</ProcessViewer>
      <DotNetActivityType>0</DotNetActivityType>
      <Projects />
      <AllProcessVariables />
      <ExportOnlyDocumentGroupIdentityDetails>false</ExportOnlyDocumentGroupIdentityDetails>
      <SiteDetailsRequired>false</SiteDetailsRequired>
      <CmisSiteDetailsRequired>false</CmisSiteDetailsRequired>
      <DocumentTemplates />
      <Assets />
      <PerceptiveSiteDetailsRequired>false</PerceptiveSiteDetailsRequired>
      <IncludeExportConnectorMappings>false</IncludeExportConnectorMappings>
      <IsSpaExport>false</IsSpaExport>
      <ProcessType>BusinessProcess</ProcessType>
      <ProtectedItems />
      <ExportPageRenditions>false</ExportPageRenditions>
      <ExportReportingTags>false</ExportReportingTags>
      <ExportTestPlans>false</ExportTestPlans>
      <IncludeProcessAssociationsInPackage>false</IncludeProcessAssociationsInPackage>
      <IsGitExport>false</IsGitExport>
    </ProcessExportOption>
    <WorkAllocationRules />
    <Skins />
    <BusinessRules />
    <Assets />
    <Forms />
    <FormTemplates />
    <FormExportOptions>
      <ExportHeader>false</ExportHeader>
      <ExportNavigation>false</ExportNavigation>
      <ExportGlobalVariables>true</ExportGlobalVariables>
      <ExportWebServices>false</ExportWebServices>
      <ExportBusinessRules>false</ExportBusinessRules>
      <ExportSecurityTokens>false</ExportSecurityTokens>
      <ExportSecurityRoles>false</ExportSecurityRoles>
      <ExportRoleMembers>false</ExportRoleMembers>
      <ProcessExportOptions>
        <ExportResources>false</ExportResources>
        <ExportGroupResourceMembers>false</ExportGroupResourceMembers>
        <ExportResourcesExtensions>false</ExportResourcesExtensions>
        <ExportCategories>false</ExportCategories>
        <WithCategoryParentage>false</WithCategoryParentage>
        <GeneralizedExport>false</GeneralizedExport>
        <ExportDotNetReferencesWithPath>true</ExportDotNetReferencesWithPath>
        <ExportCaseFragments>false</ExportCaseFragments>
        <ExportTemplateSkins>false</ExportTemplateSkins>
        <ExportExtractionClassificationData>true</ExportExtractionClassificationData>
        <ExportGlobalDataModels>false</ExportGlobalDataModels>
        <ExportProcessDataModels>false</ExportProcessDataModels>
        <ExportType>CombineAssociatedMaps</ExportType>
        <Version>0</Version>
        <ExportServerVariables>true</ExportServerVariables>
        <XmlExpressionVariables />
        <PreloadScript>1</PreloadScript>
        <SleepDuration>0</SleepDuration>
        <CategoryIds />
        <ProcessDocument>false</ProcessDocument>
        <ProcessViewer>false</ProcessViewer>
        <DotNetActivityType>0</DotNetActivityType>
        <Projects />
        <AllProcessVariables />
        <ExportOnlyDocumentGroupIdentityDetails>false</ExportOnlyDocumentGroupIdentityDetails>
        <SiteDetailsRequired>false</SiteDetailsRequired>
        <CmisSiteDetailsRequired>false</CmisSiteDetailsRequired>
        <DocumentTemplates />
        <Assets />
        <PerceptiveSiteDetailsRequired>false</PerceptiveSiteDetailsRequired>
        <IncludeExportConnectorMappings>false</IncludeExportConnectorMappings>
        <IsSpaExport>false</IsSpaExport>
        <ProcessType>BusinessProcess</ProcessType>
        <ProtectedItems />
        <ExportPageRenditions>false</ExportPageRenditions>
        <ExportReportingTags>false</ExportReportingTags>
        <ExportTestPlans>false</ExportTestPlans>
        <IncludeProcessAssociationsInPackage>false</IncludeProcessAssociationsInPackage>
        <IsGitExport>false</IsGitExport>
      </ProcessExportOptions>
      <IsSpaExport>false</IsSpaExport>
      <ProtectedItems />
    </FormExportOptions>
    <Navigations />
    <Sites />
    <Themes />
    <Languages />
    <Lookups />
    <Resources />
    <Entities />
    <WorkTypes />
    <Checklists />
    <DataModels>
      <DataModelIdentity>
        <Id>A56EB4A28B6258122BA66C88C3D917AE</Id>
        <Version>4</Version>
        <Name>TestSavedDatamodel</Name>
      </DataModelIdentity>
    </DataModels>
    <Folders>
      <FolderTypeIdentity>
        <Id>699417D9A4BD68B21C1E992D1F030B88</Id>
        <AutomaticallyPopulate>false</AutomaticallyPopulate>
        <Version>3</Version>
        <Name>TestSavedFldr</Name>
      </FolderTypeIdentity>
    </Folders>
    <ExtractionGroups />
    <ClassificationGroups />
    <Formatters />
    <FieldValidators />
    <ChecklistItems />
    <Events />
    <Targets />
    <Alerts />
    <AlertExportOption>
      <ExportAssociatedProcess>false</ExportAssociatedProcess>
    </AlertExportOption>
    <Categories>
      <CategoryIdentity>
        <Id>62E18169A4724202B42EBF7C3FDAF9E9</Id>
        <AutomaticallyPopulate>true</AutomaticallyPopulate>
        <Name>GIT DATA</Name>
      </CategoryIdentity>
    </Categories>
    <ScanVrsProfiles />
    <PdfGenerationProfiles />
    <DocumentConversionProfiles />
    <JobSchedules />
    <RegularExpressions />
    <Personas />
    <SeparationProfiles />
    <Queries />
    <ShowProcessAssociations>true</ShowProcessAssociations>
    <ShowFormAssociations>true</ShowFormAssociations>
    <SystemExportOptions>
      <IncludeNoteTypes>false</IncludeNoteTypes>
      <IncludeHotKeys>false</IncludeHotKeys>
      <IncludePageRenditions>false</IncludePageRenditions>
      <IncludeNodeColors>false</IncludeNodeColors>
      <IncludeReportingTags>false</IncludeReportingTags>
      <IncludeErrorCodes>false</IncludeErrorCodes>
    </SystemExportOptions>
    <ShowCategoryAssociations>false</ShowCategoryAssociations>
    <Packages />
    <ProtectedItemsData>
      <ProtectAllItems>false</ProtectAllItems>
      <ProtectedItems />
    </ProtectedItemsData>
    <DocumentTypeVariantCollection />
    <MissingAssociations />
    <IncludeRoleMembers>false</IncludeRoleMembers>
    <IncludeDevices>false</IncludeDevices>
    <IncludeDeviceProfiles>false</IncludeDeviceProfiles>
    <IncludeDeviceSettings>false</IncludeDeviceSettings>
    <Deployments />
    <ErrorList />
    <CaptureControlLayouts />
    <CustomServiceIdentities />
    <CustomServiceGroupIdentities />
    <CaptureSolutionIdentity>
      <Id />
      <Name />
      <Version>0</Version>
    </CaptureSolutionIdentity>
    <ImportConnections />
    <ImportSources />
    <OAuthServers />
    <QuickApp>
      <Id />
      <Name />
      <Version>0</Version>
    </QuickApp>
    <GitFolderName>qwerty</GitFolderName>
    <PackageItemAssociations>
      <PackageItemAssociation>
        <Id>62E18169A4724202B42EBF7C3FDAF9E9</Id>
        <Name />
        <ItemType>28</ItemType>
        <AssociatedItems />
      </PackageItemAssociation>
      <PackageItemAssociation>
        <Id>2C3638ABABB1C0FA631FC560A1696BC0</Id>
        <Name />
        <ItemType>0</ItemType>
        <AssociatedItems>
          <AssociatedItem>
            <Id>62E18169A4724202B42EBF7C3FDAF9E9</Id>
            <ItemType>28</ItemType>
            <Name>GIT DATA</Name>
          </AssociatedItem>
          <AssociatedItem>
            <Id>2C3638ABABB1C0FA631FC560A1696BC0</Id>
            <ItemType>0</ItemType>
            <Name>TestSavedCd</Name>
          </AssociatedItem>
          <AssociatedItem>
            <Id>3ED872430D2C1F299F96199716FE964E</Id>
            <ItemType>0</ItemType>
            <Name>TestSavedFrag</Name>
          </AssociatedItem>
        </AssociatedItems>
      </PackageItemAssociation>
      <PackageItemAssociation>
        <Id>3ED872430D2C1F299F96199716FE964E</Id>
        <Name />
        <ItemType>0</ItemType>
        <AssociatedItems />
      </PackageItemAssociation>
      <PackageItemAssociation>
        <Id>699417D9A4BD68B21C1E992D1F030B88</Id>
        <Name />
        <ItemType>19</ItemType>
        <AssociatedItems>
          <AssociatedItem>
            <Id>62E18169A4724202B42EBF7C3FDAF9E9</Id>
            <ItemType>28</ItemType>
            <Name>GIT DATA</Name>
          </AssociatedItem>
          <AssociatedItem>
            <Id>699417D9A4BD68B21C1E992D1F030B88</Id>
            <ItemType>19</ItemType>
            <Name>TestSavedFldr</Name>
          </AssociatedItem>
        </AssociatedItems>
      </PackageItemAssociation>
      <PackageItemAssociation>
        <Id>A56EB4A28B6258122BA66C88C3D917AE</Id>
        <Name />
        <ItemType>44</ItemType>
        <AssociatedItems>
          <AssociatedItem>
            <Id>62E18169A4724202B42EBF7C3FDAF9E9</Id>
            <ItemType>28</ItemType>
            <Name>GIT DATA</Name>
          </AssociatedItem>
        </AssociatedItems>
      </PackageItemAssociation>
    </PackageItemAssociations>
    <GlobalVariables />
    <ServerVariables />
    <DotNetReferences />
  </Data>
  <Comments />
  <ResourceAccessTokens>
    <ResourceAccess>
      <ResourceIdentity>
        <Id>7DF43CCDF24611D2804B00104B71BD15</Id>
        <AutomaticallyPopulate>true</AutomaticallyPopulate>
        <Name>Everyone</Name>
        <ResourceType>GroupOfWorkers</ResourceType>
        <EmailAddress />
        <UserId />
        <ManagerialLevel>0</ManagerialLevel>
      </ResourceIdentity>
      <AccessType>MaintenanceAccess</AccessType>
      <PermissionType>FullControl</PermissionType>
    </ResourceAccess>
  </ResourceAccessTokens>
  <PermissionType>NoAccess</PermissionType>
</SpaPackage>